ensverif.py
ensverif-0.1.0.dist-info/LICENSE.txt
ensverif-0.1.0.dist-info/METADATA
ensverif-0.1.0.dist-info/WHEEL
ensverif-0.1.0.dist-info/top_level.txt
ensverif-0.1.0.dist-info/RECORD
