Metadata-Version: 2.1
Name: ensverif
Version: 0.1.0
Summary: ensverif package
Author-email: Marie-Amelie Boucher <marie-emelie.boucher@usherbrooke.ca>
Project-URL: Homepage, https://github.com/TheDroplets/ensverif
Project-URL: Bug Tracker, https://github.com/TheDroplets/ensverif/issues
Classifier: Programming Language :: Python :: 3
Classifier: License :: OSI Approved :: GNU General Public License v3 (GPLv3)
Classifier: Operating System :: OS Independent
Requires-Python: >=3.7
License-File: LICENSE.txt
